kts/__init__.py
kts/__version__.py
kts/settings.py
kts/api/__init__.py
kts/api/decorators.py
kts/api/helper.py
kts/cli/__init__.py
kts/cli/default_config.toml
kts/cli/scripts.py
kts/cli/utils.py
kts/core/__init__.py
kts/core/cache.py
kts/core/feature_set.py
kts/core/frame.py
kts/core/init.py
kts/core/lists.py
kts/core/run_id.py
kts/core/types.py
kts/core/backend/__init__.py
kts/core/backend/address_manager.py
kts/core/backend/io.py
kts/core/backend/progress.py
kts/core/backend/ray_middleware.py
kts/core/backend/run_manager.py
kts/core/backend/signal.py
kts/core/backend/stats.py
kts/core/backend/util.py
kts/core/backend/worker.py
kts/core/feature_constructor/__init__.py
kts/core/feature_constructor/base.py
kts/core/feature_constructor/generic.py
kts/core/feature_constructor/parallel.py
kts/core/feature_constructor/user_defined.py
kts/eda/__init__.py
kts/eda/importance.py
kts/feature_selection/__init__.py
kts/feature_selection/importance_estimators.py
kts/modelling/__init__.py
kts/modelling/custom_model.py
kts/modelling/mixins.py
kts/modelling/pipeline.py
kts/modelling/stacking.py
kts/models/__init__.py
kts/models/binary.py
kts/models/common.py
kts/models/multiclass.py
kts/models/regression.py
kts/stl/__init__.py
kts/stl/api.py
kts/stl/backend.py
kts/stl/misc.py
kts/stl/numeric.py
kts/tests/__init__.py
kts/tests/conftest.py
kts/tests/test_backend.py
kts/tests/test_cache.py
kts/tests/test_feature_set.py
kts/ui/__init__.py
kts/ui/components.py
kts/ui/dashboard.py
kts/ui/docstring.py
kts/ui/feature_computing_report.py
kts/ui/feature_importances.py
kts/ui/fitting_report.py
kts/ui/highlighting.py
kts/ui/leaderboard.py
kts/ui/plotting.py
kts/ui/settings.py
kts/ui/static.py
kts/ui/theme.py
kts/util/__init__.py
kts/util/debug.py
kts/util/formatting.py
kts/util/hashing.py
kts/util/misc.py
kts/validation/__init__.py
kts/validation/experiment.py
kts/validation/leaderboard.py
kts/validation/split.py
kts/validation/validator.py
kts-0.4.0.dist-info/LICENSE
kts-0.4.0.dist-info/METADATA
kts-0.4.0.dist-info/WHEEL
kts-0.4.0.dist-info/entry_points.txt
kts-0.4.0.dist-info/top_level.txt
kts-0.4.0.dist-info/RECORD
