Metadata-Version: 2.1
Name: kts
Version: 0.4.0
Summary: A framework for fast and interactive conducting machine learning experiments on tabular data
Home-page: https://github.com/konodyuk/kts
Author: Nikita Konodyuk
Author-email: konodyuk@gmail.com
License: UNKNOWN
Keywords: Machine Learning,Parallel Computing,Feature Engineering
Platform: UNKNOWN
Classifier: Development Status :: 3 - Alpha
Classifier: Intended Audience :: Developers
Classifier: Intended Audience :: Education
Classifier: Intended Audience :: Science/Research
Classifier: Topic :: Scientific/Engineering :: Artificial Intelligence
Classifier: License :: OSI Approved :: MIT License
Classifier: Programming Language :: Python :: 3.6
Classifier: Programming Language :: Python :: 3.7
Classifier: Operating System :: MacOS
Classifier: Operating System :: POSIX :: Linux
Requires-Dist: ray (>=0.8.1)
Requires-Dist: pandas
Requires-Dist: numpy
Requires-Dist: scikit-learn
Requires-Dist: matplotlib
Requires-Dist: cloudpickle
Requires-Dist: dill
Requires-Dist: feather-format
Requires-Dist: click
Requires-Dist: xxhash
Requires-Dist: pygments
Requires-Dist: ipython
Requires-Dist: psutil
Requires-Dist: toml
Requires-Dist: category-encoders
Requires-Dist: docstring-parser
Provides-Extra: all
Requires-Dist: catboost ; extra == 'all'
Requires-Dist: xgboost ; extra == 'all'
Requires-Dist: lightgbm ; extra == 'all'
Requires-Dist: skorch ; extra == 'all'
Requires-Dist: ray[tune] ; extra == 'all'
Provides-Extra: hpo
Requires-Dist: ray[tune] ; extra == 'hpo'
Provides-Extra: models
Requires-Dist: catboost ; extra == 'models'
Requires-Dist: xgboost ; extra == 'models'
Requires-Dist: lightgbm ; extra == 'models'
Requires-Dist: skorch ; extra == 'models'
